{"word":"advanced","phonetic":"[ədˈvænst]","explains":["adj. 先进的；高级的，高等的；晚期的，状况不佳的；高龄的；新提出（尚未被广泛接受）的","v. 行进；发展，进步；预付（advance 的过去式和过去分词形式）"],"wordGroup":["advanced technology 先进技术","advanced level n. （英国）一般学历证书考试优等（等于A level）","advanced science 先进科学；尖端科学","advanced control [计]先行控制","advanced research 先进研究；远景研究","advanced stage [医]晚期","advanced treatment 深度处理；高级处理","advanced education 高等教育；继续教育","advanced course 预先熟练；高级课程","advanced mathematics 高等数学","advanced country 先进国家；发达国家","advanced study 进修；高级的研究","advanced development 提前开发；高级研制","advanced age 高龄，老年","advanced training 进阶训练；高级训练","advanced cancer 晚期癌症","advanced economy 先进经济体系；发达的经济","advanced search 高级搜索","advanced model 先进模型","advanced material 先进材料；尖端物料"],"sentences":[{"en":"Oil shares advanced amid economic recovery hopes.","cn":"在一片经济复苏的希望中石油股票价格上涨。"},{"en":"He was a man of advanced years.","cn":"他年事已高。"},{"en":"They had advanced 20 miles by nightfall.","cn":"夜幕降临时，他们已推进了20英里。"}]}
