{"word":"analytic","phonetic":"[ˌænəˈlɪtɪk]","explains":["adj. 分析的，分析性的（=analytical）；具备分析能力的，善于分析的（=analytical）；逻辑必然的；（语言）分析性的"],"wordGroup":["analytic method 分析法；解析法","analytic solution 解析解法，分析解","analytic geometry 解析几何；分析几何学","analytic expression 解析式；分析式","analytic function 解析函数","analytic philosophy 分析哲学；解析哲学","space analytic geometry 空间解析几何","analytic thinking 分析思维","analytic language 分析性语言"],"sentences":[{"en":"For one thing, excellent writing ability is beneficial to people's logical think and analytic ability.","cn":"一方面，优秀的写作能力有利于人们的逻辑思维和分析能力。"},{"en":"Linda, co-founder of Scores, a leading digital analytic company, established her organization on a simple premise.","cn":"领先的斯科尔数字分析公司的联合创始人琳达，在简易的前提下建立了自己的组织。"},{"en":"Would I still be analytic?","cn":"我还会有这样的分析能力吗？"}]}
