{"word":"campus","phonetic":"[ˈkæmpəs]","explains":["n. （大学或学院的）校园；大学生活；大学（学校、医院等机构的）场地","【名】 （Campus）（英）坎帕斯，（意、罗）坎普斯，（法）康皮斯（人名）"],"wordGroup":["on campus adv. 在校内","campus culture 校园文化","campus network 校园网；园区网","on the campus 校园内","campus life 校园生活","off campus 在校外；不住校","campus activities 校园活动；校内活动（campus activity的复数形式）","campus recruiting 校园招聘","campus song n. 校园歌曲"],"sentences":[{"en":"\"We're not on the main campus.\"—\"No.\"","cn":"“我们不在主校园。”—“是的。”"},{"en":"There are three dining halls on campus.","cn":"校园里有三个餐厅。"},{"en":"He was accepted into the most popular clique on campus.","cn":"他被吸收到了校园里最受欢迎的小团体里。"}]}
