{"word":"destination","phonetic":"[ˌdestɪˈneɪʃn]","explains":["n. 目的地，终点，目标","adj. 作为目的地的"],"wordGroup":["tourist destination 旅游胜地；旅游目的地；旅游景点","port of destination 目的港","final destination 最终目的地","destination port 目的港；目的端口","ultimate destination 最终目的地","destination airport 目的地机场；到达机场","destination node 目的节点；目标节点","country of destination 目的国；收货地国家","destination country 前往目的地国；到达国","destination address 目标地址","place of destination 目的地","destination folder 目标文件夹","destination directory [计]目标目录，目的目录","destination file 目标文件；结果文件"],"sentences":[{"en":"Our luggage was checked all the way through to our final destination.","cn":"我们的行李一直被托运到最终目的地。"},{"en":"At last, after twenty hours on the boat, they arrived at their destination.","cn":"乘船二十小时之后，他们终于到达了目的地。"},{"en":"He gets you to your destination without turning the trip into a white-knuckle experience.","cn":"他会将你安然无恙地送达你的目的地。"}]}
