{"word":"didactic","phonetic":"[daɪˈdæktɪk]","explains":["adj. 说教的；教诲的"],"wordGroup":[],"sentences":[{"en":"This obligation included both entertainment and instruction, which are not, says Baima odds with one another in these books, nor is entertainment the sweet coating on a didactic pill.","cn":"这个义务包括娱乐和教育，贝姆认为，这两者在这些书中并不相互矛盾，娱乐也不是说教的糖衣。"},{"en":"This obligation included both entertainment and instruction, which are not, says Baym, at odds with one another in these books, nor is entertainment the sweet coating on a didactic pill.","cn":"贝姆说，这种义务既包括娱乐也包括指导，在这些书中两者并不矛盾，娱乐也不是披在说教药丸上的甜蜜外衣。"},{"en":"He is more didactic in his approach to the learning process.","cn":"他对学习过程采用的方法是比较说教式的。"}]}
