{"word":"elemental","phonetic":"[ˌelɪˈmentl]","explains":["adj. 基本的；主要的；自然力的；四大要素的（土、水、气、火）","n. （古希腊）四元素的精灵； 基本原理"],"wordGroup":["elemental analysis 元素分析","elemental sulfur 元素硫","elemental composition 构成的化学元素"],"sentences":[{"en":"Each elemental unit has a simple layout consisting of a rectangular box and a triangular roof.","cn":"每个元素单元都有一个包括矩形框架和三角形屋顶的简单布局。"},{"en":"Even nitrogen, which is a gas in its elemental state, is normally absorbed from the soil as nitrate ions.","cn":"即使是元素状态为气体的氮，也通常作为硝酸根离子从土壤中被吸收。"},{"en":"\"Social norms are primitive and elemental,\" says Dr. Robert Cialdini, author of Influence: The Psychology of Persuasion.","cn":"“社会规范是原始的和基本的。”罗伯特·恰尔迪尼，《影响力：说服的心理学》的作者说。"}]}
