{"word":"experience","phonetic":"[ɪkˈspɪriəns]","explains":["n. 经历，往事；经验，阅历；传统","v. 经历，遭遇；体会到，感受到"],"wordGroup":["experience in 有经验；有…的经验","working experience 工作经验；工作经历","work experience 工作经验","rich experience 丰富的经验","practical experience 实务经验，实践经验，实际经验","life experience 生活经历，生活经验","personal experience 个人经验","valuable experience 宝贵的经验","professional experience 工作经验；工作经历；职业经验","user experience 用户体验","new experience 新体验","relevant experience 相关工作经验","learning experience 学习经验","past experience 过去的经验","service experience 服务经验；运行经验","by experience 凭经验；通过经验","business experience 商业经验；工作经历","operating experience 运行经验，运营经验","gain experience 获得经验","emotional experience 情感体验；情绪体验"],"sentences":[{"en":"It was a chastening experience.","cn":"那是一次令人遗憾的经历。"},{"en":"It was a cathartic experience.","cn":"那是一次情感宣泄的体验。"},{"en":"It was a tremendous experience.","cn":"这是个了不起的经历。"}]}
