{"word":"export","phonetic":"[ɪkˈspɔːrt; ˈekspɔːrt]","explains":["v. 出口；传播，输出；（在计算机中）导出，输出","n. 出口，输出；出口物，输出品；出口量，出口收入","adj. 出口的"],"wordGroup":["import and export 进出口；导入和导出；输入和输出","export trade 出口贸易；出口商","export commodities 出口商品","export tax 出口税","export market 出口市场","import and export corporation [经]进出口公司","export license 出口许可证","export sales 外销","export credit 出口信贷，出口借款","export enterprise 出口企业","export all 导出所有","export processing zone 出口加工区","export agent 出口代理；出口代理商","export control 出口控制，出口管制","export product 出口产品","export credit insurance 出口信用保险；输出信用保险；出口信贷保险","export price 出口价，出口价格","export licence 出口许可证，输出许可证","export declaration 出口申报单","export department 出口部；外销部"],"sentences":[{"en":"Ghana's main export is cocoa.","cn":"加纳的主要出口产品是可可。"},{"en":"Our main export is rice.","cn":"我们主要出口大米。"},{"en":"Then the fruit is packaged for export.","cn":"然后水果便包装出口。"}]}
