{"word":"finger","phonetic":"[ˈfɪŋɡər]","explains":["n. 手指；（手套的）手指部分；（酒在杯中的深度）一指宽；指状物；竖中指；指针","v. 用手指触摸；<美>告发，告密；拨弄（乐器）；用某种指法演奏（乐曲）；给（乐谱）标明指法符号","【名】 （Finger）（英、德、捷）芬格，（俄）芬格尔（人名）"],"wordGroup":["middle finger 中指","index finger 食指","little finger 小指","ring finger 无名指","finger print 指纹；指印","green fingers 搞园艺的才能；绿手指","finger tip 指尖；（射箭等用的）指尖套","finger ring 戒指","lift a finger 尽举手之劳","finger joint 指形接合","finger out 尖灭","finger food 手指食物；小点心","third finger n. 无名指","put the finger on [美国俚语] , ◎(向警察)告密，告发 , ◎指出被劫的现场、被谋杀的对象等，指出杀人的凶手、犯罪地点等 , [美国俚语] 见 finger","first finger 食指","finger nail 指甲","lay a finger on v. 触碰；动手打","finger mark n. 指纹；指痕","trigger finger 扣扳机的手指","have sticky fingers 有偷窃习惯，是小偷"],"sentences":[{"en":"Harrison dislocated a finger.","cn":"哈里森让一根手指脱臼了。"},{"en":"He wagged a disapproving finger.","cn":"他摇摇手指表示不赞成。"},{"en":"He kept his finger on the trigger.","cn":"他的手指一直勾着扳机。"}]}
