{"word":"fixing","phonetic":"[ˈfɪksɪŋ]","explains":["n. 固定，加固；（螺丝钉等）紧固件（常复数）；烹饪配料；特定用途的器械；作弊","v. （使）固定；确定，决定；安排，组织；修理，校正；解决，处理；集中（注意力），凝视；提供，准备；梳洗，整理；操纵，作弊；惩罚；（摄影）定影；瞄准；阉割（动物）（fix 的现在分词）"],"wordGroup":["price fixing 限价，价格管制；价格垄断","fixing agent 固色剂；固定剂","fixing device 固定装置","position fixing 定位；定座标","fixing bolt 紧固螺栓；固定螺栓","fixing bath 定影液；固着浴；定影冲洗"],"sentences":[{"en":"It's difficult to pin her down to fixing a date for a meeting.","cn":"让她确定个开会日期实在是难。"},{"en":"Are you good at fixing printers?","cn":"你擅长修理打印机吗？"},{"en":"I am fixing my sink.","cn":"我在修理我的水池。"}]}
