{"word":"holly","phonetic":"[ˈhɑːli]","explains":["n. 冬青树（等于 holm oak）","adj. 冬青属植物的","n. （Holly）人名；（英、德、捷、罗）霍利；（西）奥利"],"wordGroup":[],"sentences":[{"en":"The tinsel and the holly were decorating the drug store.","cn":"金属丝和冬青树装饰着药店。"},{"en":"Sophie Conran, the scion of the design dynasty, uses holly and ivy with berries, eucalyptus and pine cones to decorate her home.","cn":"索菲·康兰是设计王朝的后裔，她用冬青树、常青藤、浆果、桉树和松果来装饰自己的家。"},{"en":"This could be the leaves turning from green to yellow or red, the leaves falling to the ground, or the first signs of holly berries.","cn":"这可能是叶子从绿色变成黄色或红色，叶子落在地上，或冬青浆果的第一个迹象。"}]}
