{"word":"let","phonetic":"[let]","explains":["v. 允许，同意（某人做某事）；任由，让（某事发生）；（用于提出建议或表示赞同）让我们；允许（去某处）；（表示不关心）让，随； （提出帮助时说）让，由；（提出请求或布置任务时说）要；（表达祈祷或强烈的愿望）让；（用于引出要说的话）让我，我来；（计算时说）假设，设；（用于将他人的注意力引向下面的话题）让我们；（表示犹豫或思考）让我想想；（表示认为某人应该做某事）让；出租（房屋或土地）；（将工程）承包给某一竞标者； <古> 妨碍，阻碍","n. <英>出租，租借； <英>（房屋的）租期；待租房，可出租房产；（网球等发球时的）擦网球","【名】 （Let）（缅）莱，（俄）莱特（人名）"],"wordGroup":["let us 让我们","let go 放开；释放；发射","let me see 让我看看；让我想一想","let me tell you 让我告诉你；老实告诉你","let it be [口]随他（它）去；任他（它）那样","let you know 让你知道","let go of 释放，松手放开","let it go 任它去，放下","let out v. 放出；泄露；出租","let's say 比如说（用作插入语）","let you go 让你走","let's face it 面对现实吧","let you down 让你失望","let me down 让我失望","let down 使失望；放下；辜负；减速下降","let off 放出；准许…暂停工作；宽恕","let me try 让我试一试","let in 让…进来；嵌入","let slip 错过；无意中吐露；放走","let it fly 让它飞"],"sentences":[{"en":"Let her pay—she's loaded.","cn":"让她付钱吧—她富得很。"},{"en":"Let your body relax.","cn":"让你的身体放松。"},{"en":"Now let me think...","cn":"嗯，让我想想…"}]}
