{"word":"marine","phonetic":"[məˈriːn]","explains":["adj. 海洋的，海产的；海运的，海事的","n. 水兵，海军陆战队士兵；（一个国家的）船舶","【名】 （Marine）（英）马林，（西）马里内（人名）"],"wordGroup":["marine environment 海洋环境","marine engineering 轮机工程；船舶工程","marine insurance 海上保险","marine diesel 船用柴油机","marine industry n. 海洋经济产业，水产业","marine biology 海洋生物学","marine transportation 海上运输","marine diesel engine 船用柴油机","marine traffic 海上交通","marine pollution 海洋污染；海水污染","marine science 海洋科学；海洋研究","marine equipment 船用设备；水上设备；航海设备","marine engine 船用发动机；船用引擎","marine geology 海洋地质学","marine mammal 海产哺乳动物","marine sediments 海洋沈积物","marine animal 海洋动物，海洋生物","marine organism 海洋生物","marine product 海产；船用产品；水产品","marine transport 海上运输；海运"],"sentences":[{"en":"Bezanik is diving to collect marine organisms.","cn":"贝赞尼克正在潜水采集海洋生物。"},{"en":"Marine mammals generally swim with the current.","cn":"海洋哺乳动物一般顺水而游。"},{"en":"Marine life was discovered at depths previously thought to be azoic.","cn":"在先前被认为没有任何生命迹象的海洋深处发现了海洋生物。"}]}
