{"word":"monitor","phonetic":"[ˈmɑːnɪtər]","explains":["n. 显示器，监控器；监视仪，监护仪；监督员，监察员；（学校里的）班长，级长；（电台的）监听员；扬声器；巨蜥；浅水重炮舰","v. 监视；监听（外国广播或电话）；监控（无线电或电视传输信号）"],"wordGroup":["monitor system 监控系统；执行系统","computer monitor 电脑显示器","remote monitor 遥控监视器；远距离监控装置","video monitor 显示器；视频监视器","pressure monitor 压力监测器","lcd monitor 液晶显示器","display monitor 监视器；显示监视器","blood pressure monitor 血压监护仪","class monitor 班长","tv monitor 电视监视器","monitor screen 监视屏","line monitor 线路监听器","fire monitor 防火监控器","patient monitor 病人监护仪","performance monitor 性能监控器","christian science monitor 基督教科学箴言报","television monitor 电视监视器","color monitor [计]彩色监视器","power monitor 功率监控器，功率检查装置","digital monitor 数字监视器"],"sentences":[{"en":"Your doctor will monitor your blood pressure.","cn":"你的医生会监测你的血压。"},{"en":"The heart monitor shows low levels of consciousness.","cn":"心脏监控器显示低意识水平。"},{"en":"Officials had not been allowed to monitor the voting.","cn":"官员们未曾获许监控选举。"}]}
