{"word":"nationalism","phonetic":"[ˈnæʃnəlɪzəm]","explains":["n. 国家主义，民族主义；民族自豪感，民族优越感；民族自决主义；民族特征（或习惯，惯用语）"],"wordGroup":["economic nationalism 经济民族主义，经济国家主义","black nationalism 黑人民族主义；黑人国家主义"],"sentences":[{"en":"I think we'd better leave the subject of nationalism.","cn":"我想我们最好不要再谈论民族主义这个话题了。"},{"en":"His speech presented racist ideas under the guise of nationalism.","cn":"他的讲话以民族主义为幌子宣扬种族主义思想。"},{"en":"The country slipped into a dangerous mixture of nationalism and militarism.","cn":"该国陷入了一种民族主义和军国主义并存的危险境地。"}]}
