{"word":"nominal","phonetic":"[ˈnɑːmɪnl]","explains":["adj. 名义上的，有名无实的；（金额）微不足道的，象征性的；名词的，名词性的；（数量或价值）票面的；（主要用于太空旅行）运行正常的，令人满意的"],"wordGroup":["nominal value [化]标称值；票面价值","nominal diameter 公称直径；标称直径","nominal gdp 名义国内生产总值","nominal interest rate [经]名义利率","nominal pressure 公称压力；标称压力","nominal exchange rate 名义汇率","nominal stress 名义应力；公称应力","nominal power 标称功率","nominal data 名目数据；标定数据","nominal size 公称尺寸；毛尺寸；标称尺寸","nominal price 名义上的价格；虚价","nominal capacity 额定容量；公称容积"],"sentences":[{"en":"Inflation would be lower and so nominal rates would be more attractive in real terms.","cn":"通货膨胀将要降低，所以名义汇率实际上会更有吸引力。"},{"en":"We only pay a nominal rent.","cn":"我们只象征性地付一点租金。"},{"en":"I am prepared to sell my shares at a nominal price.","cn":"我准备以低价卖掉我的股票。"}]}
