{"word":"nursing","phonetic":"[ˈnɜːrsɪŋ]","explains":["n. 护理；看护；养育","v. 看护；养育（nurse 的 ing 形式）"],"wordGroup":["nursing care 护理","nursing staff 护理人员","nursing home 私人疗养院","nursing department 护理部","nursing personnel 护理人员","nursing school 护理学院","surgical nursing 外科护理学","nursing psychology 护理心理学","psychiatric nursing 精神病护理"],"sentences":[{"en":"She had no aptitude for nursing.","cn":"她没有从事护理工作的能力。"},{"en":"Nursing is not just a job—it's a vocation.","cn":"护理不仅仅是一项工作，而且还是一种职业。"},{"en":"Nursing was ill-paid and grindingly hard work.","cn":"护理工作报酬低而且工作强度令人难以忍受。"}]}
