{"word":"overhead","phonetic":"[ˌoʊvərˈhed; ˈoʊvərˌhed]","explains":["adv. 在头顶上方，在空中","adj. 头顶上的，在空中的，高架的；（驱动装置）顶置式的；经费的，管理费用的","n. <美>经常开支，营运费用（=<英>overheads）；（用于投影仪显示文字、图片等的）透明幻灯片；（尤指飞机的）顶舱"],"wordGroup":["overhead transmission 天轴","overhead crane 桥式吊车，高架起重机","overhead transmission line 架空输电线；高架输电线路","overhead line 架空线路；架空管道","overhead projector n. 高射投影仪","overhead cost 间接费用，间接成本","factory overhead 制造费用；间接制造成本","overhead light 顶灯，高架照明灯","overhead power line 架空电力线路","overhead bin 锅顶仓，吊挂箱；舱顶行李箱","overhead road 高架道路","overhead system 架空系统","overhead expense 营业费用；企业管理费用","general overhead 一般间接费用","overhead travelling crane 天车；桥式起重机","no overhead 不准超车"],"sentences":[{"en":"An eagle circled high overhead.","cn":"一只鹰在头顶上空盘旋。"},{"en":"Thunder exploded overhead.","cn":"雷声在头顶上炸开。"},{"en":"Thunder crashed overhead.","cn":"头顶上雷声隆隆。"}]}
