{"word":"precious","phonetic":"[ˈpreʃəs]","explains":["adj. 宝贵的，珍贵的；珍视的，重要的；珍稀的，珍奇的；<非正式>（表示气愤）宝贝似的；（言行）矫揉造作的，过分讲究的；<美，非正式>可爱的，讨人喜欢的","n. （用作称呼）宝贝，亲爱的","adv. 非常，极其","【名】 （Precious）（英）普雷舍斯，普雷舍丝（人名）"],"wordGroup":["precious metal 贵金属，贵重金属","precious stone 宝石","precious moment 珍贵的时刻"],"sentences":[{"en":"You're wasting precious time!","cn":"你在浪费宝贵的时间！"},{"en":"Her family's support is particularly precious to Josie.","cn":"家人的支持对乔茜尤为珍贵。"},{"en":"A family break allows you to spend precious time together.","cn":"一次家庭休假使你有机会和家人共度宝贵时光。"}]}
