{"word":"region","phonetic":"[ˈriːdʒən]","explains":["n. 地区，区域；行政区；<英>（首都以外的）地方（the regions）；身体部位；领域，界"],"wordGroup":["autonomous region 自治区","administrative region 行政区域；行政分区","special administrative region 特别行政区","in the region of adv. 在…的附近","central region 中心区","economic region 经济区","border region 边界地区","coastal region 沿岸区域，滨海区","mediterranean region 地中海区；地中海地域","local region 局部区域","source region 源区；发源地","feasible region [化]可行域；[计]可行区域；[经]可行性区域","arid region 干旱区域，干旱地区；干燥区","polar region 极地；近极区域","transition region [植]过渡区；[物]渡越区","active region 活动区；作用区","critical region 临界区；判别区域","geographic region 地理区域","growing region 生长区","peripheral region 周围区域"],"sentences":[{"en":"Much of the region is lowland.","cn":"这地区大部分是低洼地。"},{"en":"This region is steeped in tradition.","cn":"这个地区有着深厚的传统。"},{"en":"The region is glutted with hospitals.","cn":"该地区的医院供过于求。"}]}
