{"word":"rehabilitation","phonetic":"[ˌriːəˌbɪlɪˈteɪʃn]","explains":["n. 康复，复原；（权利、名誉的）恢复；修复，翻新"],"wordGroup":["rehabilitation center 修复中心","rehabilitation medicine 康复医学；复健医学","rehabilitation therapy 康复治疗；复健治疗","rehabilitation project 康复工程","vocational rehabilitation 职业康复；职业复健；职业更新；职业复原辅导"],"sentences":[{"en":"A number of other techniques are now being used by psychologists in the rehabilitation of young offenders.","cn":"一些别的技术现正被心理学家们用于年轻罪犯的复原。"},{"en":"Strong government support has made adaptive rehabilitation a reality in Boston.","cn":"政府的大力支持使适应性康复在波士顿成为现实。"},{"en":"On campus, he quickly found that beyond ordinary counselling, the university had no services for students who were undergoing physical rehabilitation and suffering from depression like him.","cn":"在学校里，他很快发现，除了普通的心理咨询，学校没有为那些像他一样正在进行身体康复和患有抑郁症的学生提供任何服务。"}]}
