{"word":"sack","phonetic":"[sæk]","explains":["n. 麻布（或厚纸、塑料等）大袋；一袋（的量）；<非正式> 解雇（the sack）；<非正式> 床（the sack）；（通常指在战争中）洗劫，劫掠；<非正式>（棒球）垒；（在争球线后对四分卫的）擒杀；宽松直筒连衣裙（=sack dress）；<史>宽松女袍；<史>（流行于18世纪、系于礼服裙裙肩上的）宽褶后拖曳地裙裾；<史>萨克葡萄酒","v. <非正式> 解雇，开除；（军队或军事集团）劫掠，洗劫；（在美式足球中）擒抱（四分卫）；<美，非正式>把……装进袋里；<美，非正式>上床睡觉（sack out）","【名】 （Sack）（英、法、葡、瑞典）萨克，（德）扎克（人名）"],"wordGroup":["hit the sack 睡觉；就寝","sack out 睡觉","sack paper 纸袋；制袋用纸","sack in v. 睡觉"],"sentences":[{"en":"Four hundred workers face the sack.","cn":"四百名工人面临解雇的危险。"},{"en":"They got through a sack of potatoes.","cn":"他们把一麻袋土豆吃完了。"},{"en":"With a mighty heave he lifted the sack onto the truck.","cn":"他用劲一举，把大麻袋扔到卡车上。"}]}
