{"word":"show","phonetic":"[ʃoʊ]","explains":["v. 显示，表明；给……看，出示；（通过示范）教，解说；指给某人看，指出；带领，引领；（情感、品质等的）流露，表露；（对某人）表现出，对待；显示出，流露出；容易显出，容易看到；标示，表明（信息、时间、计量）；描绘，表现（为）；放映，播出；展示，展出；<非正式> 证明，表明；如约赶到，露面；替（动物）报名参加比赛；出现（盈利或亏损）；<非正式> （妇女）已显出身孕；（北美）获得第三名（或前三名）","n. 演出，歌舞表演；（电视或广播）节目；展览，展览会；（体现内心感受的）动作，行为；装出的样子，虚假的外观；鲜艳悦目的景象；<非正式> 事情，场面；<非正式> 表现；动物比赛；场面，场合；<非正式> 滑稽场面，洋相；（分娩或月经时的）见红，现血，血先露；<非正式> （做某事的）机会，时机","【名】 （Show）（美、巴西）肖（人名）"],"wordGroup":["show oneself 露面","on show 展览着，在公开展出","show up 露面；露出；揭露","show in 领入；领人","show off 炫耀；卖弄","in show 外表上；有名无实地","tv show n. 电视节目","for show 为了外表，为了装门面，为引起注意；为炫耀","talk show 脱口秀；访谈节目","fashion show 时装秀；时装表演会","put on a show 假装给人家看；装病","trade show 贸易展览；内部预映","show business 娱乐业；娱乐性行业（等于showbiz）","show itself v. 呈现；可看出","show signs of 显示…迹象","slide show 放映幻灯片","variety show 综艺节目；杂耍表演","talent show 才艺表演会；业余演出比赛","motor show 汽车展览会","television show 电视节目"],"sentences":[{"en":"The show was just awesome.","cn":"演出实在棒极了。"},{"en":"The show starts promisingly enough.","cn":"演出在开始时还不错。"},{"en":"It was the first show to use the F-word and show nudity on stage.","cn":"这是第一个使用脏字并且裸体上台的演出。"}]}
