{"word":"specificity","phonetic":"[ˌspesɪˈfɪsəti]","explains":["n. [免疫] 特异性；特征；专一性"],"wordGroup":[],"sentences":[{"en":"We explore the sensitivity and specificity of in situ hybridization in human papillomavirus in condyloma acuminata tissues.","cn":"我们探讨原位分子杂交法诊断尖锐湿疣的敏感性与特异性。"},{"en":"This paper studied sensitivity, specificity and practical value and significance of ELISA in the detection of antibodies against Fasciolopsis buski in human sera.","cn":"研究了姜片吸虫成虫冷浸抗原检测姜片吸虫病患者血清抗体的敏感性和特异性及其在流行病和临床上的应用价值。"},{"en":"specificity; 4.","cn":"3. 特异性；"}]}
