{"word":"storyteller","phonetic":"[ˈstɔːritelər]","explains":["n. 说故事的人；故事作者；短篇小说作家"],"wordGroup":[],"sentences":[{"en":"With fairy tales, however, the location is generally unspecified, no matter who the storyteller is.","cn":"然而，在童话故事中，不管讲故事的人是谁，故事发生的地点一般都是不具体的。"},{"en":"Every storyteller, or, maybe every town, might have had a slightly different version of the same folktale.","cn":"每一个讲故事的人，或者在每一个城镇，关于同一个民间田的版本都可能又细微差别。"},{"en":"In the case of folktales, each storyteller would specify a particular location and time, though the time and location would differ for different storytellers.","cn":"在民间故事中，每个讲故事的人都会指定一个特定的地点和时间，尽管时间和地点会因讲故事的人不同而发生改变。"}]}
