{"word":"substance","phonetic":"[ˈsʌbstəns]","explains":["n. 物质，材料；主旨，主要内容；重要性；真实性，可信性；毒品；财富，财产；实质，（实在的）东西；<哲> 实体；可靠，稳定；（哲）实体"],"wordGroup":["in substance 实质上；基本上；事实上","organic substance 有机物；有机物质","active substance 活性物质；放射性物质；有效物质","substance abuse 物质滥用；滥用药物","mineral substance 矿物质","suspended substance 悬浮物","substance p P物质；[化]肽物质（即神经传递介质）","harmful substance 有害物质","toxic substance 有毒物","reference substance 对照品；标准物；参考物","simple substance [化]单质","working substance [化]工作介质；工作物","hazardous substance 有害物质；危险物品","inorganic substance 无机物质","ground substance 基质","poisonous substance 有毒物，毒性物质","foreign substance 外来杂质","pure substance 纯净物；纯物质；纯正物","nutrient substance 营养物质；营养素","amount of substance 物质的量"],"sentences":[{"en":"Petrol is a volatile substance.","cn":"汽油是挥发性物质。"},{"en":"Clay is a plastic substance.","cn":"黏土是可塑物质。"},{"en":"The substance polymerizes to form a hard plastic.","cn":"这种物质聚合形成坚硬的塑料。"}]}
