{"word":"tank","phonetic":"[tæŋk]","explains":["n. （储存液体或气体的）箱，罐，缸；一箱，一罐（的量）；坦克；人工蓄水池；<美，非正式> （警察局或监狱的）牢房；（养鱼、蛇等用的）玻璃容器，玻璃缸；水柜机车（tank engine 的简称）；紧身背心（多为羊毛的外罩）（tank top 的简称）","v. 彻底失败，破产；故意输掉比赛；给车辆加油；<英，非正式> 喝醉；<主苏格兰，非正式> 使惨败；把······贮放在柜（或箱，缸，罐）内；<英，非正式>乘车快速行进","【名】 （Tank）（德、土、阿塞、土库、挪）汤克（人名）"],"wordGroup":["oil tank 油箱，油槽","water tank 水箱；水槽","storage tank 储油罐；储蓄槽","fuel tank 燃料箱","in the tank 跳水；坐牢","fish tank 鱼缸，金鱼缸","tank farm 油库；油罐区","think tank 智囊团","gas tank 煤气筒，煤气罐；汽车之油箱","sedimentation tank 沉淀池；沉积槽","tank bottom 槽底","tank car 油罐车；洒水车","surge tank 缓冲槽；平衡水箱；通风油箱（等于surge chamber）","tank reactor 釜式反应器；罐式反应堆","roof tank 天台贮水箱；屋顶水箱","oil storage tank 储油槽，贮油箱","aeration tank [工程]曝气池","floating roof tank 浮顶罐，浮顶油罐","septic tank 化粪池","fermentation tank 发酵罐"],"sentences":[]}
