{"word":"weaving","phonetic":"[ˈwiːvɪŋ]","explains":["n. 编织；纺织物","v. 编，织；（用……）编成；编造（故事等）；迂回行进（weave的现在分词）","n. （Weaving）（美、英、加、澳、法）威文（人名）"],"wordGroup":["weaving machine 织布机"],"sentences":[{"en":"She is skilled at spinning and weaving.","cn":"她是纺织能手。"},{"en":"Weaving and knitting are traditional cottage industries.","cn":"编织和针织是传统的家庭手工业。"},{"en":"Originally, silkworm farming was solely restricted to women, and it was they who were responsible for the growing, harvesting and weaving.","cn":"最初，养蚕只是妇女的工作，她们负责养蚕、收割和织布。"}]}
