{"word":"wellness","phonetic":"[ˈwelnəs]","explains":["n. 健康"],"wordGroup":[],"sentences":[{"en":"This report corresponds with the existing scientific literature on bedtime and wellness.","cn":"这份报告与现有的有关就寝时间和健康的科学文献相一致。"},{"en":"Wellness may perhaps best be viewed not as a state that people can achieve, but as an ideal that people can strive for.","cn":"也许最好不要把健康看作是一种可以实现的状态，而是一种可以为之奋斗的理想状态。"},{"en":"By focusing attention on healthy ways of living, the concept of wellness can have a beneficial impact on the ways in which people face the challenges of daily life.","cn":"通过关注健康的生活方式，健康的概念可以对人们面对日常挑战的方式产生有益的影响。"}]}
