{"word":"win","phonetic":"[wɪn]","explains":["v. （在战斗、比赛、游戏等中）赢，获胜；赢得（奖品等）；通过努力得到（某物）；为……赢得，使……获得；采（矿）；晾（干草）","n. （在比赛、竞赛等中的）胜利","【名】 （Win）（德、荷、缅）温，（英）温（女子教名 Winifred 的昵称）（人名）"],"wordGroup":["win over 说服，胜诉；争取到…","win at 在…取胜","win against 赢，打败","win back 重获","win on 影响；胜过","win victory 赢得胜利","win out 最后获得成功","win through 完成","win approval 得到支持，获得通过","stand to win 一定赢","attitude to win 渴望胜利","born to win 天生大赢家；强者的诞生；生而为赢","win hands down 轻易获胜；毫不费劲地跑赢（赛马）","win first prize 赢得头奖；获一等奖；得第一名"],"sentences":[{"en":"Everyone has a chance to win.","cn":"每个人都有机会赢。"},{"en":"She loves to win an argument.","cn":"她喜欢在辩论中获胜。"},{"en":"They didn't deserve to win.","cn":"他们不该赢。"}]}
