{"word":"wound","phonetic":"[wuːnd]","explains":["n. （刀、枪或其他武器所致的）创伤，伤口；（感情或名誉的）损害，痛苦","v. （武器或其他利器）伤害，使受伤；（在感情上）使受创伤","v. 蜿蜒；使喘不过气；缠绕（wind 的过去式和过去分词形式）"],"wordGroup":["wound healing 创伤修复，愈合；伤口愈合","wound up 紧张的；兴奋的","wound dressing 绷带，伤口敷料；创伤敷料","spiral wound [医]螺旋状伤","wire wound 绕线型，线绕式","wound gasket 缠绕垫","open wound 开放性创伤；裸露的伤口","spiral wound gasket 金属缠绕垫；缠绕式垫片","flesh wound 轻伤，皮肉之伤；皮肉伤","wound rotor 绕线转子，绕线端子","puncture wound 刺伤，穿刺伤"],"sentences":[{"en":"Blood oozed out of the wound.","cn":"血从伤口慢慢流出来。"},{"en":"The nurse cleaned the wound.","cn":"护士清洗了伤口。"},{"en":"The wound was oozing blood.","cn":"伤口流着血。"}]}
